MANIFEST.in
README.md
setup.py
query_reports/__init__.py
query_reports/admin.py
query_reports/models.py
query_reports/test_urls.py
query_reports/tests.py
query_reports/urls.py
query_reports/views.py
query_reports.egg-info/PKG-INFO
query_reports.egg-info/SOURCES.txt
query_reports.egg-info/dependency_links.txt
query_reports.egg-info/not-zip-safe
query_reports.egg-info/pbr.json
query_reports.egg-info/requires.txt
query_reports.egg-info/top_level.txt
query_reports/fixtures/test_query_reports.json
query_reports/migrations/0001_initial.py
query_reports/migrations/__init__.py
query_reports/templates/base.html
query_reports/templates/query_reports/base.html
query_reports/templates/query_reports/bootstrap_base.html
query_reports/templates/query_reports/index.html
query_reports/templates/query_reports/show.html
query_reports/templatetags/__init__.py
query_reports/templatetags/query_reports_tags.py